{
  "locations": [
    {
      "conference": "DC26",
      "updated_at": "2018-06-30T18:57+0000",
      "name": "Track 2",
      "id": 26001
    },
    {
      "conference": "DC26",
      "updated_at": "2018-06-30T18:57+0000",
      "name": "101 Track, Flamingo",
      "id": 26002
    },
    {
      "conference": "DC26",
      "updated_at": "2018-06-30T18:57+0000",
      "name": "Track 1",
      "id": 26003
    },
    {
      "conference": "DC26",
      "updated_at": "2018-06-30T18:57+0000",
      "name": "Track 3",
      "id": 26004
    },
    {
      "conference": "DC26",
      "updated_at": "2018-06-30T18:57+0000",
      "name": "Location:TBA",
      "id": 26005
    }
  ],
  "updated_at": "2018-06-30T18:57+0000"
}